[
  {
    "Recipe": "Salmon",
    "Ingredient": "Salmon",
    "Unit": "Pounds",
    "Quantity": 1.75,
    "Category": "Meat"
  },
  {
    "Recipe": "Salmon",
    "Ingredient": "Jalapeno",
    "Unit": "Each",
    "Quantity": 1,
    "Category": "Produce"
  },
  {
    "Recipe": "Salmon",
    "Ingredient": "Cilantro",
    "Unit": "Each",
    "Quantity": 1,
    "Category": "Produce"
  },
  {
    "Recipe": "Salmon",
    "Ingredient": "Red Onion",
    "Unit": "Each",
    "Quantity": 1,
    "Category": "Produce"
  },
  {
    "Recipe": "Salmon",
    "Ingredient": "Lime",
    "Unit": "Each",
    "Quantity": 1,
    "Category": "Produce"
  },
  {
    "Recipe": "Salmon",
    "Ingredient": "Mango",
    "Unit": "Each",
    "Quantity": 2,
    "Category": "Produce"
  },
  {
    "Recipe": "Caesar",
    "Ingredient": "Chicken Breast",
    "Unit": "Pounds",
    "Quantity": 2,
    "Category": "Meat"
  },
  {
    "Recipe": "Caesar",
    "Ingredient": "Romaine Lettuce",
    "Unit": "Each",
    "Quantity": 1,
    "Category": "Produce"
  },
  {
    "Recipe": "Caesar",
    "Ingredient": "Croutons",
    "Unit": "Each",
    "Quantity": 1,
    "Category": "Bread"
  },
  {
    "Recipe": "Caesar",
    "Ingredient": "Shredded Parmesan",
    "Unit": "Each",
    "Quantity": 1,
    "Category": "Cheese"
  },
  {
    "Recipe": "Caesar",
    "Ingredient": "Caesar Dressing",
    "Unit": "Each",
    "Quantity": 1,
    "Category": "Cooking"
  },
  {
    "Recipe": "Basil",
    "Ingredient": "Chicken Thigh",
    "Unit": "Pounds",
    "Quantity": 2,
    "Category": "Meat"
  },
  {
    "Recipe": "Basil",
    "Ingredient": "Red Potato",
    "Unit": "Each",
    "Quantity": 3,
    "Category": "Produce"
  },
  {
    "Recipe": "Basil",
    "Ingredient": "Lemon",
    "Unit": "Each",
    "Quantity": 1,
    "Category": "Produce"
  },
  {
    "Recipe": "Basil",
    "Ingredient": "Basil",
    "Unit": "Each",
    "Quantity": 2,
    "Category": "Produce"
  },
  {
    "Recipe": "Basil",
    "Ingredient": "Shallot",
    "Unit": "Each",
    "Quantity": 1,
    "Category": "Produce"
  },
  {
    "Recipe": "Tandoori",
    "Ingredient": "Chicken Thigh",
    "Unit": "Pounds",
    "Quantity": 2,
    "Category": "Meat"
  },
  {
    "Recipe": "Tandoori",
    "Ingredient": "Cauliflower",
    "Unit": "Each",
    "Quantity": 1,
    "Category": "Produce"
  },
  {
    "Recipe": "Tandoori",
    "Ingredient": "Carrot",
    "Unit": "Each",
    "Quantity": 1,
    "Category": "Produce"
  },
  {
    "Recipe": "Tandoori",
    "Ingredient": "Red Onion",
    "Unit": "Each",
    "Quantity": 1,
    "Category": "Produce"
  },
  {
    "Recipe": "Tandoori",
    "Ingredient": "Cilantro",
    "Unit": "Each",
    "Quantity": 1,
    "Category": "Produce"
  },
  {
    "Recipe": "Tandoori",
    "Ingredient": "Lemon",
    "Unit": "Each",
    "Quantity": 1,
    "Category": "Produce"
  },
  {
    "Recipe": "Avocado",
    "Ingredient": "Chicken Breast",
    "Unit": "Pounds",
    "Quantity": 1,
    "Category": "Meat"
  },
  {
    "Recipe": "Avocado",
    "Ingredient": "Avocado",
    "Unit": "Each",
    "Quantity": 2,
    "Category": "Produce"
  },
  {
    "Recipe": "Avocado",
    "Ingredient": "Canned Corn",
    "Unit": "Each",
    "Quantity": 1,
    "Category": "Canned"
  },
  {
    "Recipe": "Avocado",
    "Ingredient": "Lemon",
    "Unit": "Each",
    "Quantity": 1,
    "Category": "Produce"
  },
  {
    "Recipe": "Avocado",
    "Ingredient": "Red Onion",
    "Unit": "Each",
    "Quantity": 1,
    "Category": "Produce"
  },
  {
    "Recipe": "Avocado",
    "Ingredient": "Grape Tomatoes",
    "Unit": "Each",
    "Quantity": 1,
    "Category": "Produce"
  },
  {
    "Recipe": "Avocado",
    "Ingredient": "Cucumber",
    "Unit": "Each",
    "Quantity": 1,
    "Category": "Produce"
  },
  {
    "Recipe": "Avocado",
    "Ingredient": "Yellow Bell Pepper",
    "Unit": "Each",
    "Quantity": 1,
    "Category": "Produce"
  },
  {
    "Recipe": "Avocado",
    "Ingredient": "Cilantro",
    "Unit": "Each",
    "Quantity": 1,
    "Category": "Produce"
  },
  {
    "Recipe": "Taco Bowl",
    "Ingredient": "Ground Beef",
    "Unit": "Pounds",
    "Quantity": 1,
    "Category": "Meat"
  },
  {
    "Recipe": "Taco Bowl",
    "Ingredient": "Lettuce",
    "Unit": "Each",
    "Quantity": 1,
    "Category": "Produce"
  },
  {
    "Recipe": "Taco Bowl",
    "Ingredient": "Tomato",
    "Unit": "Each",
    "Quantity": 1,
    "Category": "Produce"
  },
  {
    "Recipe": "Taco Bowl",
    "Ingredient": "Sour Cream",
    "Unit": "Each",
    "Quantity": 1,
    "Category": "Dairy"
  },
  {
    "Recipe": "Taco Bowl",
    "Ingredient": "Doritos",
    "Unit": "Each",
    "Quantity": 1,
    "Category": "Chips"
  },
  {
    "Recipe": "Taco Bowl",
    "Ingredient": "Taco Powder",
    "Unit": "Each",
    "Quantity": 1,
    "Category": "Cooking"
  },
  {
    "Recipe": "Taco Bowl",
    "Ingredient": "Canned Corn",
    "Unit": "Each",
    "Quantity": 1,
    "Category": "Canned"
  },
  {
    "Recipe": "Taco Bowl",
    "Ingredient": "Avocado",
    "Unit": "Each",
    "Quantity": 2,
    "Category": "Produce"
  },
  {
    "Recipe": "Taco Bowl",
    "Ingredient": "Mexican Cheese",
    "Unit": "Each",
    "Quantity": 1,
    "Category": "Cheese"
  },
  {
    "Recipe": "Vermicelli",
    "Ingredient": "Chicken Thigh",
    "Unit": "Pounds",
    "Quantity": 2,
    "Category": "Meat"
  },
  {
    "Recipe": "Vermicelli",
    "Ingredient": "Vermicelli Noodles",
    "Unit": "Each",
    "Quantity": 1,
    "Category": "Asian"
  },
  {
    "Recipe": "Vermicelli",
    "Ingredient": "Cucumber",
    "Unit": "Each",
    "Quantity": 1,
    "Category": "Produce"
  },
  {
    "Recipe": "Vermicelli",
    "Ingredient": "Cilantro",
    "Unit": "Each",
    "Quantity": 1,
    "Category": "Produce"
  },
  {
    "Recipe": "Vermicelli",
    "Ingredient": "Lime",
    "Unit": "Each",
    "Quantity": 1,
    "Category": "Produce"
  },
  {
    "Recipe": "Staples",
    "Ingredient": "Rice",
    "Unit": "Each",
    "Quantity": 1,
    "Category": "Rice"
  },
  {
    "Recipe": "Staples",
    "Ingredient": "Water Bottles",
    "Unit": "Each",
    "Quantity": 1,
    "Category": "Water"
  },
  {
    "Recipe": "Staples",
    "Ingredient": "Topo Chico",
    "Unit": "Each",
    "Quantity": 1,
    "Category": "Water"
  },
  {
    "Recipe": "Staples",
    "Ingredient": "Eggs",
    "Unit": "Each",
    "Quantity": 1,
    "Category": "Dairy"
  },
  {
    "Recipe": "Staples",
    "Ingredient": "Grapes",
    "Unit": "Each",
    "Quantity": 1,
    "Category": "Produce"
  },
  {
    "Recipe": "Staples",
    "Ingredient": "Tortillas",
    "Unit": "Each",
    "Quantity": 1,
    "Category": "Tortilla"
  },
  {
    "Recipe": "Staples",
    "Ingredient": "Crackers",
    "Unit": "Each",
    "Quantity": 1,
    "Category": "Crackers"
  },
  {
    "Recipe": "Staples",
    "Ingredient": "Whole Milk",
    "Unit": "Each",
    "Quantity": 1,
    "Category": "Dairy"
  },
  {
    "Recipe": "Options",
    "Ingredient": "Strawberries",
    "Unit": "Each",
    "Quantity": 1,
    "Category": "Produce"
  },
  {
    "Recipe": "Options",
    "Ingredient": "Butter",
    "Unit": "Each",
    "Quantity": 1,
    "Category": "Dairy"
  },
  {
    "Recipe": "Options",
    "Ingredient": "Big Red",
    "Unit": "Each",
    "Quantity": 1,
    "Category": "Soda"
  },
  {
    "Recipe": "Options",
    "Ingredient": "Dr. Pepper",
    "Unit": "Each",
    "Quantity": 1,
    "Category": "Soda"
  },
  {
    "Recipe": "Options",
    "Ingredient": "Fish Sauce",
    "Unit": "Each",
    "Quantity": 1,
    "Category": "Asian"
  },
  {
    "Recipe": "Options",
    "Ingredient": "Red Wine Vinegar",
    "Unit": "Each",
    "Quantity": 1,
    "Category": "Cooking"
  },
  {
    "Recipe": "Options",
    "Ingredient": "Extra Virgin Olive Oil",
    "Unit": "Each",
    "Quantity": 1,
    "Category": "Cooking"
  },
  {
    "Recipe": "Options",
    "Ingredient": "Bagels",
    "Unit": "Each",
    "Quantity": 1,
    "Category": "Bread"
  },
  {
    "Recipe": "Options",
    "Ingredient": "Cream Cheese",
    "Unit": "Each",
    "Quantity": 1,
    "Category": "Dairy"
  },
  {
    "Recipe": "Options",
    "Ingredient": "Decaf Coffee",
    "Unit": "Each",
    "Quantity": 1,
    "Category": "Coffee"
  },
  {
    "Recipe": "Options",
    "Ingredient": "Salt",
    "Unit": "Each",
    "Quantity": 1,
    "Category": "Cooking"
  }
]